{"cookies":[{"name":"_gid","value":"GA1.2.332915165.1698393740","domain":".practicetestautomation.com","path":"/","expires":1.6984801E+09,"httpOnly":false,"secure":false,"sameSite":"Lax"},{"name":"_gat_gtag_UA_41419453_6","value":"1","domain":".practicetestautomation.com","path":"/","expires":1.6983939E+09,"httpOnly":false,"secure":false,"sameSite":"Lax"},{"name":"_ga","value":"GA1.1.1026388038.1698393740","domain":".practicetestautomation.com","path":"/","expires":1.7329537E+09,"httpOnly":false,"secure":false,"sameSite":"Lax"},{"name":"_ga_K4LEK94WN3","value":"GS1.1.1698393739.1.0.1698393744.0.0.0","domain":".practicetestautomation.com","path":"/","expires":1.7329537E+09,"httpOnly":false,"secure":false,"sameSite":"Lax"}],"origins":[]}